{"name":"crayola.css","items":[{"key":"CRAYOLA_Red","value":"#ED0A3F"},{"key":"CRAYOLA_Maroon","value":"#C32148"},{"key":"CRAYOLA_Scarlet","value":"#FD0E35"},{"key":"CRAYOLA_Brick_Red","value":"#C62D42"},{"key":"CRAYOLA_English_Vermilion","value":"#CC474B"},{"key":"CRAYOLA_Madder_Lake","value":"#CC3336"},{"key":"CRAYOLA_Permanent_Geranium_Lake","value":"#E12C2C"},{"key":"CRAYOLA_Maximum_Red","value":"#D92121"},{"key":"CRAYOLA_Indian_Red","value":"#B94E48"},{"key":"CRAYOLA_Orange-Red","value":"#FF5349"},{"key":"CRAYOLA_Sunset_Orange","value":"#FE4C40"},{"key":"CRAYOLA_Bittersweet","value":"#FE6F5E"},{"key":"CRAYOLA_Dark_Venetian_Red","value":"#B33B24"},{"key":"CRAYOLA_Venetian_Red","value":"#CC553D"},{"key":"CRAYOLA_Light_Venetian_Red","value":"#E6735C"},{"key":"CRAYOLA_Vivid_Tangerine","value":"#FF9980"},{"key":"CRAYOLA_Middle_Red","value":"#E58E73"},{"key":"CRAYOLA_Burnt_Orange","value":"#FF7F49"},{"key":"CRAYOLA_Red-Orange","value":"#FF681F"},{"key":"CRAYOLA_Orange","value":"#FF8833"},{"key":"CRAYOLA_Macaroni_and_Cheese","value":"#FFB97B"},{"key":"CRAYOLA_Middle_Yellow_Red","value":"#ECB176"},{"key":"CRAYOLA_Mango_Tango","value":"#E77200"},{"key":"CRAYOLA_Yellow-Orange","value":"#FFAE42"},{"key":"CRAYOLA_Maximum_Yellow_Red","value":"#F2BA49"},{"key":"CRAYOLA_Banana_Mania","value":"#FBE7B2"},{"key":"CRAYOLA_Maize","value":"#F2C649"},{"key":"CRAYOLA_Orange-Yellow","value":"#F8D568"},{"key":"CRAYOLA_Goldenrod","value":"#FCD667"},{"key":"CRAYOLA_Dandelion","value":"#FED85D"},{"key":"CRAYOLA_Yellow","value":"#FBE870"},{"key":"CRAYOLA_Green-Yellow","value":"#F1E788"},{"key":"CRAYOLA_Middle_Yellow","value":"#FFEB00"},{"key":"CRAYOLA_Olive_Green","value":"#B5B35C"},{"key":"CRAYOLA_Spring_Green","value":"#ECEBBD"},{"key":"CRAYOLA_Maximum_Yellow","value":"#FAFA37"},{"key":"CRAYOLA_Canary","value":"#FFFF99"},{"key":"CRAYOLA_Lemon_Yellow","value":"#FFFF9F"},{"key":"CRAYOLA_Maximum_Green_Yellow","value":"#D9E650"},{"key":"CRAYOLA_Middle_Green_Yellow","value":"#ACBF60"},{"key":"CRAYOLA_Inchworm","value":"#AFE313"},{"key":"CRAYOLA_Light_Chrome_Green","value":"#BEE64B"},{"key":"CRAYOLA_Yellow-Green","value":"#C5E17A"},{"key":"CRAYOLA_Maximum_Green","value":"#5E8C31"},{"key":"CRAYOLA_Asparagus","value":"#7BA05B"},{"key":"CRAYOLA_Granny_Smith_Apple","value":"#9DE093"},{"key":"CRAYOLA_Fern","value":"#63B76C"},{"key":"CRAYOLA_Middle_Green","value":"#4D8C57"},{"key":"CRAYOLA_Green","value":"#3AA655"},{"key":"CRAYOLA_Medium_Chrome_Green","value":"#6CA67C"},{"key":"CRAYOLA_Forest_Green","value":"#5FA777"},{"key":"CRAYOLA_Sea_Green","value":"#93DFB8"},{"key":"CRAYOLA_Shamrock","value":"#33CC99"},{"key":"CRAYOLA_Mountain_Meadow","value":"#1AB385"},{"key":"CRAYOLA_Jungle_Green","value":"#29AB87"},{"key":"CRAYOLA_Caribbean_Green","value":"#00CC99"},{"key":"CRAYOLA_Tropical_Rain_Forest","value":"#00755E"},{"key":"CRAYOLA_Middle_Blue_Green","value":"#8DD9CC"},{"key":"CRAYOLA_Pine_Green","value":"#01786F"},{"key":"CRAYOLA_Maximum_Blue_Green","value":"#30BFBF"},{"key":"CRAYOLA_Robins_Egg_Blue","value":"#00CCCC"},{"key":"CRAYOLA_Teal_Blue","value":"#008080"},{"key":"CRAYOLA_Light_Blue","value":"#8FD8D8"},{"key":"CRAYOLA_Aquamarine","value":"#95E0E8"},{"key":"CRAYOLA_Turquoise_Blue","value":"#6CDAE7"},{"key":"CRAYOLA_Outer_Space","value":"#2D383A"},{"key":"CRAYOLA_Sky_Blue","value":"#76D7EA"},{"key":"CRAYOLA_Middle_Blue","value":"#7ED4E6"},{"key":"CRAYOLA_Blue-Green","value":"#0095B7"},{"key":"CRAYOLA_Pacific_Blue","value":"#009DC4"},{"key":"CRAYOLA_Cerulean","value":"#02A4D3"},{"key":"CRAYOLA_Maximum_Blue","value":"#47ABCC"},{"key":"CRAYOLA_Blue_1","value":"#4997D0"},{"key":"CRAYOLA_Cerulean_Blue","value":"#339ACC"},{"key":"CRAYOLA_Cornflower","value":"#93CCEA"},{"key":"CRAYOLA_Green-Blue","value":"#2887C8"},{"key":"CRAYOLA_Midnight_Blue","value":"#00468C"},{"key":"CRAYOLA_Navy_Blue","value":"#0066CC"},{"key":"CRAYOLA_Denim","value":"#1560BD"},{"key":"CRAYOLA_Blue_3","value":"#0066FF"},{"key":"CRAYOLA_Cadet_Blue","value":"#A9B2C3"},{"key":"CRAYOLA_Periwinkle","value":"#C3CDE6"},{"key":"CRAYOLA_Blue_2","value":"#4570E6"},{"key":"CRAYOLA_Wild_Blue_Yonder","value":"#7A89B8"},{"key":"CRAYOLA_Indigo","value":"#4F69C6"},{"key":"CRAYOLA_Manatee","value":"#8D90A1"},{"key":"CRAYOLA_Cobalt_Blue","value":"#8C90C8"},{"key":"CRAYOLA_Celestial_Blue","value":"#7070CC"},{"key":"CRAYOLA_Blue_Bell","value":"#9999CC"},{"key":"CRAYOLA_Maximum_Blue_Purple","value":"#ACACE6"},{"key":"CRAYOLA_Violet-Blue","value":"#766EC8"},{"key":"CRAYOLA_Blue-Violet","value":"#6456B7"},{"key":"CRAYOLA_Ultramarine_Blue","value":"#3F26BF"},{"key":"CRAYOLA_Middle_Blue_Purple","value":"#8B72BE"},{"key":"CRAYOLA_Purple_Heart","value":"#652DC1"},{"key":"CRAYOLA_Royal_Purple","value":"#6B3FA0"},{"key":"CRAYOLA_Violet_2","value":"#8359A3"},{"key":"CRAYOLA_Medium_Violet","value":"#8F47B3"},{"key":"CRAYOLA_Wisteria","value":"#C9A0DC"},{"key":"CRAYOLA_Lavender_1","value":"#BF8FCC"},{"key":"CRAYOLA_Vivid_Violet","value":"#803790"},{"key":"CRAYOLA_Maximum_Purple","value":"#733380"},{"key":"CRAYOLA_Purple_Mountains_Majesty","value":"#D6AEDD"},{"key":"CRAYOLA_Fuchsia","value":"#C154C1"},{"key":"CRAYOLA_Pink_Flamingo","value":"#FC74FD"},{"key":"CRAYOLA_Violet_1","value":"#732E6C"},{"key":"CRAYOLA_Brilliant_Rose","value":"#E667CE"},{"key":"CRAYOLA_Orchid","value":"#E29CD2"},{"key":"CRAYOLA_Plum","value":"#8E3179"},{"key":"CRAYOLA_Medium_Rose","value":"#D96CBE"},{"key":"CRAYOLA_Thistle","value":"#EBB0D7"},{"key":"CRAYOLA_Mulberry","value":"#C8509B"},{"key":"CRAYOLA_Red-Violet","value":"#BB3385"},{"key":"CRAYOLA_Middle_Purple","value":"#D982B5"},{"key":"CRAYOLA_Maximum_Red_Purple","value":"#A63A79"},{"key":"CRAYOLA_Jazzberry_Jam","value":"#A50B5E"},{"key":"CRAYOLA_Eggplant","value":"#614051"},{"key":"CRAYOLA_Magenta","value":"#F653A6"},{"key":"CRAYOLA_Cerise","value":"#DA3287"},{"key":"CRAYOLA_Wild_Strawberry","value":"#FF3399"},{"key":"CRAYOLA_Lavender_2","value":"#FBAED2"},{"key":"CRAYOLA_Cotton_Candy","value":"#FFB7D5"},{"key":"CRAYOLA_Carnation_Pink","value":"#FFA6C9"},{"key":"CRAYOLA_Violet-Red","value":"#F7468A"},{"key":"CRAYOLA_Razzmatazz","value":"#E30B5C"},{"key":"CRAYOLA_Pig_Pink","value":"#FDD7E4"},{"key":"CRAYOLA_Carmine","value":"#E62E6B"},{"key":"CRAYOLA_Blush","value":"#DB5079"},{"key":"CRAYOLA_Tickle_Me_Pink","value":"#FC80A5"},{"key":"CRAYOLA_Mauvelous","value":"#F091A9"},{"key":"CRAYOLA_Salmon","value":"#FF91A4"},{"key":"CRAYOLA_Middle_Red_Purple","value":"#A55353"},{"key":"CRAYOLA_Mahogany","value":"#CA3435"},{"key":"CRAYOLA_Melon","value":"#FEBAAD"},{"key":"CRAYOLA_Pink_Sherbert","value":"#F7A38E"},{"key":"CRAYOLA_Burnt_Sienna","value":"#E97451"},{"key":"CRAYOLA_Brown","value":"#AF593E"},{"key":"CRAYOLA_Sepia","value":"#9E5B40"},{"key":"CRAYOLA_Fuzzy_Wuzzy","value":"#87421F"},{"key":"CRAYOLA_Beaver","value":"#926F5B"},{"key":"CRAYOLA_Tumbleweed","value":"#DEA681"},{"key":"CRAYOLA_Raw_Sienna","value":"#D27D46"},{"key":"CRAYOLA_Van_Dyke_Brown","value":"#664228"},{"key":"CRAYOLA_Tan","value":"#D99A6C"},{"key":"CRAYOLA_Desert_Sand","value":"#EDC9AF"},{"key":"CRAYOLA_Peach","value":"#FFCBA4"},{"key":"CRAYOLA_Burnt_Umber","value":"#805533"},{"key":"CRAYOLA_Apricot","value":"#FDD5B1"},{"key":"CRAYOLA_Almond","value":"#EED9C4"},{"key":"CRAYOLA_Raw_Umber","value":"#665233"},{"key":"CRAYOLA_Shadow","value":"#837050"},{"key":"CRAYOLA_Raw_Sienna_1","value":"#E6BC5C"},{"key":"CRAYOLA_Timberwolf","value":"#D9D6CF"},{"key":"CRAYOLA_Gold_1","value":"#92926E"},{"key":"CRAYOLA_Gold_2","value":"#E6BE8A"},{"key":"CRAYOLA_Silver","value":"#C9C0BB"},{"key":"CRAYOLA_Copper","value":"#DA8A67"},{"key":"CRAYOLA_Antique_Brass","value":"#C88A65"},{"key":"CRAYOLA_Black","value":"#000000"},{"key":"CRAYOLA_Charcoal_Gray","value":"#736A62"},{"key":"CRAYOLA_Gray","value":"#8B8680"},{"key":"CRAYOLA_Blue-Gray","value":"#C8C8CD"}]}